{
  "Wins": 4074,
  "Wins1": 487,
  "Wins2": 313,
  "Wins3": 316,
  "Wins4": 282,
  "Wins5": 281,
  "Wins6": 342,
  "Wins7": 264,
  "Wins8": 355,
  "Wins9": 344,
  "Wins10": 386,
  "Wins11": 692,
  "Losses": 4961,
  "Losses1": 485,
  "Losses2": 453,
  "Losses3": 329,
  "Losses4": 452,
  "Losses5": 296,
  "Losses6": 435,
  "Losses7": 337,
  "Losses8": 494,
  "Losses9": 433,
  "Losses10": 518,
  "Losses11": 675,
  "Winrate": "45%",
  "Winrate1": "50%",
  "Winrate2": "41%",
  "Winrate3": "49%",
  "Winrate4": "38%",
  "Winrate5": "49%",
  "Winrate6": "44%",
  "Winrate7": "44%",
  "Winrate8": "42%",
  "Winrate9": "44%",
  "Winrate10": "43%",
  "Winrate11": "51%",
  "environment": "100%",
  "environment1": "11%",
  "environment2": "8%",
  "environment3": "7%",
  "environment4": "8%",
  "environment5": "6%",
  "environment6": "9%",
  "environment7": "7%",
  "environment8": "9%",
  "environment9": "9%",
  "environment10": "10%",
  "environment11": "15%"
}